{
  "count": 222,
  "stations": [
    {
      "addr": "서울특별시 중구 남대문로 92 1층 주차장",
      "chargeTp": "2",
      "cpId": "811",
      "cpNm": "급속01",
      "cpStat": "1",
      "cpTp": "10",
      "csId": "14",
      "csNm": "서울직할",
      "lat": 37.565199,
      "longi": 126.983339,
      "statUpdateDatetime": "2020-10-04 17:43:36"
    },
    {
     "addr": "서울특별시 중구 남대문로 92 1층 주차장",
      "chargeTp": "2",
      "cpId": "811",
      "cpNm": "급속01",
      "cpStat": "1",
      "cpTp": "10",
      "csId": "14",
      "csNm": "서울직할",
      "lat": 37.565199,
      "longi": 126.983339,
      "statUpdateDatetime": "2020-10-04 17:43:36"
    },
    {
       "addr": "서울특별시 중구 남대문로 92 1층 주차장",
      "chargeTp": "2",
      "cpId": "811",
      "cpNm": "급속01",
      "cpStat": "1",
      "cpTp": "10",
      "csId": "14",
      "csNm": "서울직할",
      "lat": 37.565199,
      "longi": 126.983339,
      "statUpdateDatetime": "2020-10-04 17:43:36"
    }
  ]
}